tattler/client/tattler_py/__init__.py
tattler/client/tattler_py/replay_dead_letters.py
tattler/client/tattler_py/tattler_client.py
tattler/client/tattler_py/tattler_client_http.py
tattler/client/tattler_py/tattler_client_utils.py
tattler/client/tattler_py/tattler_cmd.py
tattler/client/tattler_py/tests/test_tattler.py
tattler/client/tattler_py/tests/test_tattler_client_utils.py
tattler/client/tattler_py/tests/test_tattler_cmd.py
tattler/client/tattler_py/tests/test_tattler_http.py
tattler/client/tattler_py/tests/test_tattler_module.py
tattler/server/pluginloader.py
tattler/server/tattler_livepreview.py
tattler/server/tattler_utils.py
tattler/server/tattlersrv_http.py
tattler/server/templatemgr.py
tattler/server/templateprocessor_jinja.py
tattler/server/plugins/passthrough_addressbook_tattler_plugin.py
tattler/server/plugins/tests/test_passthrough_addressbook.py
tattler/server/sendable/__init__.py
tattler/server/sendable/blacklist.py
tattler/server/sendable/template_processor.py
tattler/server/sendable/vector_email.py
tattler/server/sendable/vector_sendable.py
tattler/server/sendable/vector_sms.py
tattler/server/sendable/tests/test_module.py
tattler/server/sendable/tests/test_sendable.py
tattler/server/sendable/tests/test_template_processor.py
tattler/server/sendable/tests/test_vector_email.py
tattler/server/sendable/tests/test_vector_sms.py
tattler/server/tests/test_livepreview.py
tattler/server/tests/test_pluginloader.py
tattler/server/tests/test_tattler_templates.py
tattler/server/tests/test_tattler_utils.py
tattler/server/tests/test_tattlersrv_http.py
tattler/server/tests/test_templatemgr.py
tattler/server/tests/test_templateprocessor_jinja.py
tattler/server/tests/testutils.py
tattler/server/tests/testutils_templates.py
tattler/server/tests/fixtures/plugin_loading_order/a_tattler_plugin.py
tattler/server/tests/fixtures/plugin_loading_order/b_tattler_plugin.py
tattler/server/tests/fixtures/plugin_loading_order/c_tattler_plugin.py
tattler-2.4.1.dist-info/licenses/LICENSE.txt
tattler-2.4.1.dist-info/METADATA
tattler-2.4.1.dist-info/WHEEL
tattler-2.4.1.dist-info/entry_points.txt
tattler-2.4.1.dist-info/top_level.txt
tattler-2.4.1.dist-info/RECORD
