Metadata-Version: 2.4
Name: tattler
Version: 2.4.1
Summary: A client-server notification system for HTML emails, sms and more.
Author-email: Michele Mazzucchi <support@tattler.dev>
Project-URL: Home, https://tattler.dev
Project-URL: Documentation, https://docs.tattler.dev/
Project-URL: Repository, https://github.com/tattler-community/tattler-community
Project-URL: Issues, https://github.com/tattler-community/tattler-community/issues
Classifier: License :: OSI Approved :: BSD License
Classifier: Programming Language :: Python :: 3 :: Only
Classifier: Operating System :: POSIX
Classifier: Development Status :: 5 - Production/Stable
Classifier: Environment :: Console
Classifier: Topic :: Communications
Requires-Python: >=3.9
License-File: LICENSE.txt
Requires-Dist: Jinja2>=3.1.6
Requires-Dist: humanize>=4.12.3
Requires-Dist: bulksms>=1.1.1
Requires-Dist: envdir>=1.0.1
Dynamic: license-file
